README.rst
setup.py
RecamanSequence/__init__.py
RecamanSequence/recaman_sequence.py
RecamanSequence.egg-info/PKG-INFO
RecamanSequence.egg-info/SOURCES.txt
RecamanSequence.egg-info/dependency_links.txt
RecamanSequence.egg-info/entry_points.txt
RecamanSequence.egg-info/top_level.txt