Metadata-Version: 2.1
Name: RecamanSequence
Version: 0.1
Summary: Iterate through Recaman's sequence up to a givenlimit, where limit represent number of desired iterations
Home-page: https://github.com/urosjevremovic/Recamans-Sequence
Author: Uros Jevremovic
Author-email: jevremovic.uros91@gmail.com
License: MIT
Platform: UNKNOWN
